{
	"id": "f9968c4a-f43d-4287-a900-d22d7c3a9643",
	"name": "venv-todoly",
	"values": [
		{
			"key": "userName",
			"value": "jpv.9pm@gmail.com",
			"type": "default",
			"enabled": true
		},
		{
			"key": "password",
			"value": "123456789",
			"type": "secret",
			"enabled": true
		},
		{
			"key": "url",
			"value": "https://todo.ly/api/",
			"type": "default",
			"enabled": true
		}
	],
	"_postman_variable_scope": "environment",
	"_postman_exported_at": "2024-11-23T04:31:34.384Z",
	"_postman_exported_using": "Postman/11.19.0"
}